async_orm/__init__.py
async_orm-1.0.0.dist-info/LICENSE
async_orm-1.0.0.dist-info/METADATA
async_orm-1.0.0.dist-info/WHEEL
async_orm-1.0.0.dist-info/top_level.txt
async_orm-1.0.0.dist-info/RECORD
