Metadata-Version: 2.1
Name: async-orm
Version: 1.0.0
Summary: async orm for async web framework
Home-page: https://github.com/kerol/async-orm
Author: kerol
Author-email: ikerol@163.com
License: UNKNOWN
Platform: UNKNOWN
Classifier: Programming Language :: Python :: 3
Classifier: License :: OSI Approved :: MIT License
Classifier: Operating System :: OS Independent
Requires-Dist: django
